MANIFEST.in
README.md
freeze-requirements.txt
setup.cfg
setup.py
tests-requirements.txt
benchmarks/__init__.py
benchmarks/accessor_bench.py
biggraphite/__init__.py
biggraphite/accessor.py
biggraphite/accessor_cache.py
biggraphite/accessor_factory.py
biggraphite/cache_factory.py
biggraphite/glob_utils.py
biggraphite/graphite_utils.py
biggraphite/metadata_cache.py
biggraphite/metric.py
biggraphite/settings.py
biggraphite/threads.py
biggraphite/tracing.py
biggraphite/utils.py
biggraphite.egg-info/PKG-INFO
biggraphite.egg-info/SOURCES.txt
biggraphite.egg-info/dependency_links.txt
biggraphite.egg-info/entry_points.txt
biggraphite.egg-info/requires.txt
biggraphite.egg-info/top_level.txt
biggraphite/cli/__init__.py
biggraphite/cli/bg_carbon_aggregator_cache.py
biggraphite/cli/bg_carbon_cache.py
biggraphite/cli/bgutil.py
biggraphite/cli/clusters_diff.py
biggraphite/cli/command.py
biggraphite/cli/command_clean.py
biggraphite/cli/command_copy.py
biggraphite/cli/command_delete.py
biggraphite/cli/command_du.py
biggraphite/cli/command_graphite_web.py
biggraphite/cli/command_info.py
biggraphite/cli/command_list.py
biggraphite/cli/command_read.py
biggraphite/cli/command_repair.py
biggraphite/cli/command_shell.py
biggraphite/cli/command_stats.py
biggraphite/cli/command_syncdb.py
biggraphite/cli/command_test.py
biggraphite/cli/command_web.py
biggraphite/cli/command_write.py
biggraphite/cli/commands.py
biggraphite/cli/import_whisper.py
biggraphite/cli/replay_traffic.py
biggraphite/cli/web/__init__.py
biggraphite/cli/web/app.py
biggraphite/cli/web/capture.py
biggraphite/cli/web/context.py
biggraphite/cli/web/filters.py
biggraphite/cli/web/worker.py
biggraphite/cli/web/namespaces/__init__.py
biggraphite/cli/web/namespaces/bgutil.py
biggraphite/cli/web/namespaces/biggraphite.py
biggraphite/cli/web/templates/index.html
biggraphite/cli/web/templates/maintenance.html
biggraphite/cli/web/templates/workers.html
biggraphite/cli/web/templates/gourde/base.html
biggraphite/drivers/__init__.py
biggraphite/drivers/_delayed_writer.py
biggraphite/drivers/_downsampling.py
biggraphite/drivers/_utils.py
biggraphite/drivers/cassandra.py
biggraphite/drivers/cassandra_common.py
