Metadata-Version: 1.2
Name: biggraphite
Version: 0.14.18
Summary: Simple Scalable Time Series Database.
Home-page: https://github.com/criteo/biggraphite
Maintainer: Criteo Graphite Team
Maintainer-email: github@criteo.com
License: Apache Software License
Keywords: graphite carbon cassandra biggraphite tsdb timeseries
Platform: UNKNOWN
Classifier: Programming Language :: Python :: 2.7
Classifier: Programming Language :: Python :: 3.6
